check_model_config/__init__.py
check_model_config/cli.py
check_model_config/tests.py
check_model_config-0.1.0.dist-info/METADATA
check_model_config-0.1.0.dist-info/WHEEL
check_model_config-0.1.0.dist-info/entry_points.txt
check_model_config-0.1.0.dist-info/licenses/LICENSE
check_model_config-0.1.0.dist-info/RECORD
