Metadata-Version: 2.4
Name: check-model-config
Version: 0.1.0
Summary: A tool to validate transformer model configurations
Author-email: Cavit Erginsoy <cavit@erginsoy.com>
License-Expression: MIT
License-File: LICENSE
Keywords: llm,pytest,transformers,validation
Requires-Python: >=3.9
Requires-Dist: accelerate>=1.2.0
Requires-Dist: pytest>=8.3.4
Requires-Dist: torch>=2.5.1
Requires-Dist: transformers>=4.47.1
